buildcpp/__init__.py
buildcpp/const.py
buildcpp/import_.py
buildcpp/utils.py
buildcpp/cmake/__init__.py
buildcpp/cmake/build.py
buildcpp/cmake/const.py
buildcpp/cmake/target.py
buildcpp-0.2.3.dist-info/licenses/LICENSE
buildcpp-0.2.3.dist-info/METADATA
buildcpp-0.2.3.dist-info/WHEEL
buildcpp-0.2.3.dist-info/top_level.txt
buildcpp-0.2.3.dist-info/RECORD
