Metadata-Version: 2.4
Name: buildcpp
Version: 0.2.3
Summary: A build system for C++.
License-Expression: MIT
Project-URL: Homepage, https://anglebase.github.io/buildcpp/
Project-URL: IssueTracker, https://github.com/Anglebase/buildcpp/issues
Requires-Python: >=3.7
License-File: LICENSE
Dynamic: license-file
